[
  {
    "id": "1",
    "btnText": "open modal",
    "modalText": "this is description for card 1."
  },
  {
    "id": "2",
    "btnText": "open modal",
    "modalText": "this is description for card 2."
  },
  {
    "id": "3",
    "btnText": "open modal",
    "modalText": "this is description for card 3."
  },
  {
    "id": "4",
    "btnText": "open modal",
    "modalText": "this is description for card 4."
  },
  {
    "id": "5",
    "btnText": "open modal",
    "modalText": "this is description for card 5."
  },
  {
    "id": "6",
    "btnText": "open modal",
    "modalText": "this is description for card 6."
  },
  {
    "id": "7",
    "btnText": "open modal",
    "modalText": "this is description for card 7."
  },
  {
    "id": "8",
    "btnText": "open modal",
    "modalText": "this is description for card 8."
  }
]